{
 "version": "auto-py-to-exe-configuration_v1",
 "pyinstallerOptions": [
  {
   "optionDest": "noconfirm",
   "value": true
  },
  {
   "optionDest": "filenames",
   "value": "E:/Python/TestMKVCreator/MKVCreator (RU).py"
  },
  {
   "optionDest": "onefile",
   "value": false
  },
  {
   "optionDest": "console",
   "value": false
  },
  {
   "optionDest": "icon_file",
   "value": "E:/Python/TestMKVCreator/app/12078684.ico"
  },
  {
   "optionDest": "clean_build",
   "value": false
  },
  {
   "optionDest": "debug",
   "value": "all"
  },
  {
   "optionDest": "strip",
   "value": false
  },
  {
   "optionDest": "noupx",
   "value": false
  },
  {
   "optionDest": "hide_console",
   "value": "hide-early"
  },
  {
   "optionDest": "disable_windowed_traceback",
   "value": false
  },
  {
   "optionDest": "version_file",
   "value": "E:/Python/TestMKVCreator/version-file.txt"
  },
  {
   "optionDest": "uac_admin",
   "value": false
  },
  {
   "optionDest": "uac_uiaccess",
   "value": false
  },
  {
   "optionDest": "argv_emulation",
   "value": false
  },
  {
   "optionDest": "bootloader_ignore_signals",
   "value": false
  },
  {
   "optionDest": "datas",
   "value": "E:/Python/TestMKVCreator/mkvtoolnix;mkvtoolnix/"
  },
  {
   "optionDest": "datas",
   "value": "E:/Python/TestMKVCreator/ffmpeg;ffmpeg/"
  },
  {
   "optionDest": "datas",
   "value": "E:/Python/TestMKVCreator/app;app/"
  }
 ],
 "nonPyinstallerOptions": {
  "increaseRecursionLimit": true,
  "manualArguments": ""
 }
}